cargo_t_x64_win_msvc/__init__.py
cargo_t_x64_win_msvc/data/LICENSE-APACHE
cargo_t_x64_win_msvc/data/LICENSE-MIT
cargo_t_x64_win_msvc/data/LICENSE-THIRD-PARTY
cargo_t_x64_win_msvc/data/README.md
cargo_t_x64_win_msvc/data/builder-config
cargo_t_x64_win_msvc/data/components
cargo_t_x64_win_msvc/data/git-commit-hash
cargo_t_x64_win_msvc/data/git-commit-info
cargo_t_x64_win_msvc/data/install.sh
cargo_t_x64_win_msvc/data/rust-installer-version
cargo_t_x64_win_msvc/data/version
cargo_t_x64_win_msvc/data/cargo/manifest.in
cargo_t_x64_win_msvc/data/cargo/bin/cargo.exe
cargo_t_x64_win_msvc/data/cargo/bin/cargo.pdb
cargo_t_x64_win_msvc/data/cargo/etc/bash_completion.d/cargo
cargo_t_x64_win_msvc/data/cargo/share/doc/cargo/LICENSE-APACHE
cargo_t_x64_win_msvc/data/cargo/share/doc/cargo/LICENSE-MIT
cargo_t_x64_win_msvc/data/cargo/share/doc/cargo/LICENSE-THIRD-PARTY
cargo_t_x64_win_msvc/data/cargo/share/doc/cargo/README.md
cargo_t_x64_win_msvc/data/cargo/share/man/man1/cargo-add.1
cargo_t_x64_win_msvc/data/cargo/share/man/man1/cargo-bench.1
cargo_t_x64_win_msvc/data/cargo/share/man/man1/cargo-build.1
cargo_t_x64_win_msvc/data/cargo/share/man/man1/cargo-check.1
cargo_t_x64_win_msvc/data/cargo/share/man/man1/cargo-clean.1
cargo_t_x64_win_msvc/data/cargo/share/man/man1/cargo-doc.1
cargo_t_x64_win_msvc/data/cargo/share/man/man1/cargo-fetch.1
cargo_t_x64_win_msvc/data/cargo/share/man/man1/cargo-fix.1
cargo_t_x64_win_msvc/data/cargo/share/man/man1/cargo-generate-lockfile.1
cargo_t_x64_win_msvc/data/cargo/share/man/man1/cargo-help.1
cargo_t_x64_win_msvc/data/cargo/share/man/man1/cargo-info.1
cargo_t_x64_win_msvc/data/cargo/share/man/man1/cargo-init.1
cargo_t_x64_win_msvc/data/cargo/share/man/man1/cargo-install.1
cargo_t_x64_win_msvc/data/cargo/share/man/man1/cargo-locate-project.1
cargo_t_x64_win_msvc/data/cargo/share/man/man1/cargo-login.1
cargo_t_x64_win_msvc/data/cargo/share/man/man1/cargo-logout.1
cargo_t_x64_win_msvc/data/cargo/share/man/man1/cargo-metadata.1
cargo_t_x64_win_msvc-0.91.0.post1.dist-info/METADATA
cargo_t_x64_win_msvc-0.91.0.post1.dist-info/WHEEL
cargo_t_x64_win_msvc-0.91.0.post1.dist-info/top_level.txt
cargo_t_x64_win_msvc-0.91.0.post1.dist-info/RECORD
